jackylee/__init__.py
jackylee/leecode.py
jackylee/test.py
jackylee/algorithm/__init__.py
jackylee/algorithm/sort.py
jackylee/algorithm/unionfind.py
jackylee/datastructure/__init__.py
jackylee/datastructure/heap.py
jackylee/datastructure/linklist.py
jackylee/datastructure/tree.py
jackylee/deeplearning/__init__.py
jackylee/deeplearning/utils.py
jackylee/game/__init__.py
jackylee/game/sudoku.py
jackylee/scripts/__init__.py
jackylee/scripts/pdfhandle.py
jackyleeutils-0.0.13.dist-info/LICENSE
jackyleeutils-0.0.13.dist-info/METADATA
jackyleeutils-0.0.13.dist-info/WHEEL
jackyleeutils-0.0.13.dist-info/top_level.txt
jackyleeutils-0.0.13.dist-info/RECORD
