Metadata-Version: 2.1
Name: jackyleeutils
Version: 0.0.13
Author: jackyleeutils
License-File: LICENSE
